cyber/__init__.py
cyber/examples/__init__.py
cyber/examples/proto/__init__.py
cyber/examples/proto/examples_pb2.py
cyber/proto/__init__.py
cyber/proto/choreography_conf_pb2.py
cyber/proto/classic_conf_pb2.py
cyber/proto/clock_pb2.py
cyber/proto/component_conf_pb2.py
cyber/proto/cyber_conf_pb2.py
cyber/proto/dag_conf_pb2.py
cyber/proto/parameter_pb2.py
cyber/proto/perception_pb2.py
cyber/proto/perf_conf_pb2.py
cyber/proto/proto_desc_pb2.py
cyber/proto/qos_profile_pb2.py
cyber/proto/record_pb2.py
cyber/proto/role_attributes_pb2.py
cyber/proto/run_mode_conf_pb2.py
cyber/proto/scheduler_conf_pb2.py
cyber/proto/simple_pb2.py
cyber/proto/topology_change_pb2.py
cyber/proto/transport_conf_pb2.py
cyber/proto/unit_test_pb2.py
modules/__init__.py
modules/audio/__init__.py
modules/audio/proto/__init__.py
modules/audio/proto/audio_common_pb2.py
modules/audio/proto/audio_conf_pb2.py
modules/audio/proto/audio_event_pb2.py
modules/audio/proto/audio_pb2.py
modules/bridge/__init__.py
modules/bridge/proto/__init__.py
modules/bridge/proto/udp_bridge_remote_info_pb2.py
modules/canbus/__init__.py
modules/canbus/proto/__init__.py
modules/canbus/proto/canbus_conf_pb2.py
modules/canbus/proto/ch_pb2.py
modules/canbus/proto/chassis_detail_pb2.py
modules/canbus/proto/chassis_pb2.py
modules/canbus/proto/devkit_pb2.py
modules/canbus/proto/ge3_pb2.py
modules/canbus/proto/lexus_pb2.py
modules/canbus/proto/neolix_edu_pb2.py
modules/canbus/proto/transit_pb2.py
modules/canbus/proto/vehicle_parameter_pb2.py
modules/canbus/proto/wey_pb2.py
modules/canbus/proto/zhongyun_pb2.py
modules/common/__init__.py
modules/common/adapters/__init__.py
modules/common/adapters/proto/__init__.py
modules/common/adapters/proto/adapter_config_pb2.py
modules/common/configs/__init__.py
modules/common/configs/proto/__init__.py
modules/common/configs/proto/vehicle_config_pb2.py
modules/common/latency_recorder/__init__.py
modules/common/latency_recorder/proto/__init__.py
record_msg-1.0.0.dist-info/LICENSE
record_msg-1.0.0.dist-info/METADATA
record_msg-1.0.0.dist-info/WHEEL
record_msg-1.0.0.dist-info/top_level.txt
record_msg-1.0.0.dist-info/RECORD
