Metadata-Version: 2.1
Name: record-msg
Version: 1.0.0
Summary: Record message parse helper function
Home-page: https://github.com/daohu527/record_msg
Author: daohu527
Author-email: daohu527@gmail.com
License: UNKNOWN
Project-URL: Bug Tracker, https://github.com/daohu527/record_msg/issues
Platform: UNKNOWN
Classifier: Programming Language :: Python :: 3
Classifier: License :: OSI Approved :: Apache Software License
Classifier: Operating System :: OS Independent
Requires-Python: >=3.6
Requires-Dist: opencv-python
Requires-Dist: lzf
